actiongate/__init__.py
actiongate/core.py
actiongate/engine.py
actiongate/store.py
actiongate-0.1.0.dist-info/METADATA
actiongate-0.1.0.dist-info/WHEEL
actiongate-0.1.0.dist-info/RECORD
