Metadata-Version: 2.4
Name: actiongate
Version: 0.1.0
Summary: Deterministic, pre-execution gating for semantic actions (e.g. tool calls) in agent systems.
Project-URL: Homepage, https://github.com/actiongate-oss/actiongate
Project-URL: Documentation, https://github.com/actiongate-oss/actiongate#readme
Project-URL: Repository, https://github.com/actiongate-oss/actiongate
Author-email: ActionGate OSS <actiongate-oss@users.noreply.github.com>
License-Expression: MIT
Keywords: agent-framework,ai-agents,llm,rate-limiting,throttling
Classifier: Development Status :: 4 - Beta
Classifier: Intended Audience :: Developers
Classifier: License :: OSI Approved :: MIT License
Classifier: Programming Language :: Python :: 3
Classifier: Programming Language :: Python :: 3.12
Classifier: Topic :: Software Development :: Libraries :: Python Modules
Classifier: Typing :: Typed
Requires-Python: >=3.12
Provides-Extra: dev
Requires-Dist: mypy>=1.0; extra == 'dev'
Requires-Dist: pytest-cov>=4.0; extra == 'dev'
Requires-Dist: pytest>=8.0; extra == 'dev'
Requires-Dist: ruff>=0.1; extra == 'dev'
Provides-Extra: redis
Requires-Dist: redis>=4.0; extra == 'redis'
